setup.py
nlp_playground/__init__.py
nlp_playground/playground.py
nlp_playground.egg-info/PKG-INFO
nlp_playground.egg-info/SOURCES.txt
nlp_playground.egg-info/dependency_links.txt
nlp_playground.egg-info/not-zip-safe
nlp_playground.egg-info/requires.txt
nlp_playground.egg-info/top_level.txt