Metadata-Version: 1.0
Name: nlp-playground
Version: 0.15
Summary: Python package for basic NLP functions
Home-page: UNKNOWN
Author: UNKNOWN
Author-email: UNKNOWN
License: UNKNOWN
Platform: UNKNOWN
